pollinations_api/__init__.py
pollinations_api/pollinations_api.py
pollinations_api-0.1.4.dist-info/licenses/LICENSE
pollinations_api-0.1.4.dist-info/METADATA
pollinations_api-0.1.4.dist-info/WHEEL
pollinations_api-0.1.4.dist-info/top_level.txt
pollinations_api-0.1.4.dist-info/RECORD
