Metadata-Version: 2.4
Name: pollinations_api
Version: 0.1.4
Summary: Python client library for Pollinations.AI API
Author-email: Justin Kang <scisjustin@gmail.com>
License-Expression: MIT
Project-URL: Homepage, https://github.com/mangostin2010/pollinations_api
Classifier: Programming Language :: Python :: 3
Requires-Python: >=3.6
License-File: LICENSE
Requires-Dist: requests
Provides-Extra: streaming
Requires-Dist: sseclient-py; extra == "streaming"
Dynamic: license-file
